Workbook

Sheet Cover Page

Sheet Historical Financial Data ($ in
A1: Metric | B1: 2021 | C1: 2022 | D1: 2023 | E1: 2024 | F1: 2025
A2: Revenue | B2: 24105 | C2: 29310 | D2: 32653 | E2: 35926 | F2: 40000
A3: EBIT (Operating Income) | B3: 15804 | C3: 18813 | D3: 21000 | E3: 23595 | F3: 23994
A4: Income Tax Expense | B4: 3752 | C4: 2924 | D4: 3764 | E4: 4173 | F4: 4136
A5: Net Income | B5: 12311 | C5: 14957 | D5: 17273 | E5: 19743 | F5: 20058
A6: Depreciation | B6: 804 | C6: 861 | D6: 943 | E6: 1034 | F6: 1220
A7: Capex | B7: 705 | C7: 970 | D7: 1059 | E7: 1257 | F7: 1482
A8: Cash | B8: 19799 | C8: 20377 | D8: 21990 | E8: 19763 | F8: 24987
A9: Debt | B9: 20977 | C9: 22450 | D9: 22214 | E9: 22563 | F9: 22635

Sheet Ratio & Trend Analysis
A1: Year | B1: 2021 | C1: 2022 | D1: 2023 | E1: 2024 | F1: 2025 | G1: Average
A2: Revenue Growth % | C2: =('Historical Financial Data ($ in'!C2-'Historical Financial Data ($ in'!B2)/'Historical Financial Data ($ in'!B2 -> 0.2159303 | D2: =('Historical Financial Data ($ in'!D2-'Historical Financial Data ($ in'!C2)/'Historical Financial Data ($ in'!C2 -> 0.11405664 | E2: =('Historical Financial Data ($ in'!E2-'Historical Financial Data ($ in'!D2)/'Historical Financial Data ($ in'!D2 -> 0.10023581 | F2: =('Historical Financial Data ($ in'!F2-'Historical Financial Data ($ in'!E2)/'Historical Financial Data ($ in'!E2 -> 0.11339977 | G2: =AVERAGE(B2:F2) -> 0.13590563
A3: EBIT Margin % | B3: ='Historical Financial Data ($ in'!B3/'Historical Financial Data ($ in'!B2 -> 0.65563161 | C3: ='Historical Financial Data ($ in'!C3/'Historical Financial Data ($ in'!C2 -> 0.64186285 | D3: ='Historical Financial Data ($ in'!D3/'Historical Financial Data ($ in'!D2 -> 0.64312621 | E3: ='Historical Financial Data ($ in'!E3/'Historical Financial Data ($ in'!E2 -> 0.65676669 | F3: ='Historical Financial Data ($ in'!F3/'Historical Financial Data ($ in'!F2 -> 0.59985 | G3: =AVERAGE(B3:F3) -> 0.63944747
A4: Tax Rate % | B4: ='Historical Financial Data ($ in'!B4/'Historical Financial Data ($ in'!B3 -> 0.23740825 | C4: ='Historical Financial Data ($ in'!C4/'Historical Financial Data ($ in'!C3 -> 0.15542444 | D4: ='Historical Financial Data ($ in'!D4/'Historical Financial Data ($ in'!D3 -> 0.1792381 | E4: ='Historical Financial Data ($ in'!E4/'Historical Financial Data ($ in'!E3 -> 0.1768595 | F4: ='Historical Financial Data ($ in'!F4/'Historical Financial Data ($ in'!F3 -> 0.17237643 | G4: =AVERAGE(B4:F4) -> 0.18426134
A5: Depreciation % of Revenue | B5: ='Historical Financial Data ($ in'!B6/'Historical Financial Data ($ in'!B2 -> 0.033354076 | C5: ='Historical Financial Data ($ in'!C6/'Historical Financial Data ($ in'!C2 -> 0.02937564 | D5: ='Historical Financial Data ($ in'!D6/'Historical Financial Data ($ in'!D2 -> 0.028879429 | E5: ='Historical Financial Data ($ in'!E6/'Historical Financial Data ($ in'!E2 -> 0.028781384 | F5: ='Historical Financial Data ($ in'!F6/'Historical Financial Data ($ in'!F2 -> 0.0305 | G5: =AVERAGE(B5:F5) -> 0.030178106
A6: Capex % of Revenue | B6: ='Historical Financial Data ($ in'!B7/'Historical Financial Data ($ in'!B2 -> 0.029247044 | C6: ='Historical Financial Data ($ in'!C7/'Historical Financial Data ($ in'!C2 -> 0.033094507 | D6: ='Historical Financial Data ($ in'!D7/'Historical Financial Data ($ in'!D2 -> 0.032431936 | E6: ='Historical Financial Data ($ in'!E7/'Historical Financial Data ($ in'!E2 -> 0.034988588 | F6: ='Historical Financial Data ($ in'!F7/'Historical Financial Data ($ in'!F2 -> 0.03705 | G6: =AVERAGE(B6:F6) -> 0.033362415

Sheet Forecasting
A1: Year | B1: Revenue | C1: EBIT | D1: Tax | E1: Depreciation | F1: Capex | G1: FCF | H1: Discount Factor | I1: PV of FCF | J1: WACC | K1: 0.09
A2: 2026 | B2: =(3840.6*A2)-7737135 -> 43920.6 | C2: =B2*63.94% -> 28082.832 | D2: =C2*18.43% -> 5175.6659 | E2: =B2*3.02% -> 1326.4021 | F2: =B2*3.34% -> 1466.948 | G2: =(C2-D2)+E2-F2 -> 22766.62 | H2: =1/(1+$K$1)^1 -> 0.91743119 | I2: =G2*H2 -> 20886.807 | J2: Terminal Growth | K2: 0.03
A3: 2027 | B3: =(3840.6*A3)-7737135 -> 47761.2 | C3: =B3*63.94% -> 30538.511 | D3: =C3*18.43% -> 5628.2476 | E3: =B3*3.02% -> 1442.3882 | F3: =B3*3.34% -> 1595.2241 | G3: =(C3-D3)+E3-F3 -> 24757.428 | H3: =1/(1+$K$1)^2 -> 0.84167999 | I3: =G3*H3 -> 20837.832
A4: 2028 | B4: =(3840.6*A4)-7737135 -> 51601.8 | C4: =B4*63.94% -> 32994.191 | D4: =C4*18.43% -> 6080.8294 | E4: =B4*3.02% -> 1558.3744 | F4: =B4*3.34% -> 1723.5001 | G4: =(C4-D4)+E4-F4 -> 26748.236 | H4: =1/(1+$K$1)^3 -> 0.77218348 | I4: =G4*H4 -> 20654.546
A5: 2029 | B5: =(3840.6*A5)-7737135 -> 55442.4 | C5: =B5*63.94% -> 35449.871 | D5: =C5*18.43% -> 6533.4111 | E5: =B5*3.02% -> 1674.3605 | F5: =B5*3.34% -> 1851.7762 | G5: =(C5-D5)+E5-F5 -> 28739.044 | H5: =1/(1+$K$1)^4 -> 0.70842521 | I5: =G5*H5 -> 20359.463
A6: 2030 | B6: =(3840.6*A6)-7737135 -> 59283 | C6: =B6*63.94% -> 37905.55 | D6: =C6*18.43% -> 6985.9929 | E6: =B6*3.02% -> 1790.3466 | F6: =B6*3.34% -> 1980.0522 | G6: =(C6-D6)+E6-F6 -> 30729.852 | H6: =1/(1+$K$1)^5 -> 0.64993139 | I6: =G6*H6 -> 19972.295
F9: Terminal Value | G9: =(G6*(1+$K$2))/($K$1-$K$2) -> 527529.12
F10: Discount Terminal Value | G10: =G9/(1+$K$1)^5 -> 342857.73
F11: Enterprise Value | G11: =SUM(I2:I6)+G10 -> 445568.68
A15: A | B15: B
A16: Year | B16: Revenue
A17: 2021 | B17: 24105
A18: 2022 | B18: 29310
A19: 2023 | B19: 32653
A20: 2024 | B20: 35926
A21: 2025 | B21: 40000

Sheet Output
A1: SUMMARY OUTPUT
A3: Regression Statistics
A4: Multiple R | B4: 0.99625939
A5: R Square | B5: 0.99253277
A6: Adjusted R Square | B6: 0.99004369
A7: Standard Error | B7: 608.19931
A8: Observations | B8: 5
A10: ANOVA
B11: df | C11: SS | D11: MS | E11: F | F11: Significance F
A12: Regression | B12: 1 | C12: 1.4750208e+08 | D12: 1.4750208e+08 | E12: 398.75515 | F12: 0.00027447593
A13: Residual | B13: 3 | C13: 1109719.2 | D13: 369906.4
A14: Total | B14: 4 | C14: 1.486118e+08
B16: Coefficients | C16: Standard Error | D16: t Stat | E16: P-value | F16: Lower 95% | G16: Upper 95% | H16: Lower 95.0% | I16: Upper 95.0%
A17: Intercept | B17: -7737135 | C17: 389082.69 | D17: -19.88558 | E17: 0.00027791774 | F17: -8975369.8 | G17: -6498900.2 | H17: -8975369.8 | I17: -6498900.2
A18: Year | B18: 3840.6 | C18: 192.32951 | D18: 19.968855 | E18: 0.00027447593 | F18: 3228.5217 | G18: 4452.6783 | H18: 3228.5217 | I18: 4452.6783

Sheet DCF Valuation
A1: Item | B1: Value
A2: Enterprise Value | B2: 445569
A3: Cash (2025) | B3: 24987
A4: Debt (2025) | B4: 22635
A5: Equity Value | B5: =B2+B3-B4 -> 447921
A6: Shares Outstanding | B6: 1714
A7: Intrinsic Value per Share | B7: =B5/B6 -> 261.33081

Sheet Sensitivity Analysis
A1: Intrinsic Value per Share Sensitivity Analysis (USD)
A2: WACC / Terminal Growth Rate | B2: 0.02 | C2: 0.03 | D2: 0.04
A3: 0.08 | B3: 270.23 | C3: 312.59 | D3: 378.12
A4: 0.09 | B4: 231.61 | C4: ='DCF Valuation'!B7 -> 261.33081 | D4: 303.39
A5: 0.1 | B5: 201.57 | C5: 223.48 | D5: 252.74
